README.md
pyproject.toml
src/pypixelmapdump/PL2FileReader64.dll
src/pypixelmapdump/__init__.py
src/pypixelmapdump/pixelmapdump.exe
src/pypixelmapdump/pixelmapdump.py
src/pypixelmapdump.egg-info/PKG-INFO
src/pypixelmapdump.egg-info/SOURCES.txt
src/pypixelmapdump.egg-info/dependency_links.txt
src/pypixelmapdump.egg-info/top_level.txt