Metadata-Version: 2.4
Name: pypixelmapdump
Version: 0.1.3
Summary: Python wrapper for Plexon's pixelmapdump utility, enabling querying of PL2 files for probe, bad channel information.
Author-email: Nikhil Chandra <nikhil@plexon.com>
Requires-Python: >=3.9
